easybacnet/__init__.py
easybacnet/manager.py
easybacnet-0.1.0.dist-info/METADATA
easybacnet-0.1.0.dist-info/WHEEL
easybacnet-0.1.0.dist-info/top_level.txt
easybacnet-0.1.0.dist-info/RECORD
