Metadata-Version: 2.1
Name: easybacnet
Version: 0.1.0
Requires-Dist: BAC0
